hangar_pil/__init__.py
hangar_pil/plugin.py
hangar_pil-0.3.2.dist-info/LICENSE
hangar_pil-0.3.2.dist-info/METADATA
hangar_pil-0.3.2.dist-info/WHEEL
hangar_pil-0.3.2.dist-info/entry_points.txt
hangar_pil-0.3.2.dist-info/top_level.txt
hangar_pil-0.3.2.dist-info/RECORD
